haja_workers/__init__.py
haja_workers/config.py
haja_workers/function.py
haja_workers/main.py
haja_workers/sdk.py
haja_workers/communication/__init__.py
haja_workers/communication/errors.py
haja_workers/communication/grpc_communicator.py
haja_workers/correlation/__init__.py
haja_workers/correlation/router.py
haja_workers/dispatcher/__init__.py
haja_workers/dispatcher/dispatcher.py
haja_workers/examples/__init__.py
haja_workers/examples/input.py
haja_workers/examples/random_output.py
haja_workers/examples/store_chat_history.py
haja_workers/grpccache/__init__.py
haja_workers/grpccache/grpccache.py
haja_workers/grpcstore/__init__.py
haja_workers/grpcstore/grpcstore.py
haja_workers/handlers/__init__.py
haja_workers/handlers/activate.py
haja_workers/handlers/inbound_workflow_handler.py
haja_workers/models/__init__.py
haja_workers/models/node_data.py
haja_workers/rpc/__init__.py
haja_workers/rpc/rpc.py
haja_workers/state/__init__.py
haja_workers/state/event_state.py
haja_workers/state/global_state.py
haja_workers/types/__init__.py
haja_workers/types/events.py
haja_workers/types/keys.py
haja_workers/types/message.py
haja_workers/utils/__init__.py
haja_workers/utils/uid.py
haja_workers/workflowsgrpc/__init__.py
haja_workers/workflowsgrpc/converters.py
haja_workers/workflowsgrpc/events_pb2.py
haja_workers/workflowsgrpc/events_pb2_grpc.py
haja_workers-0.1.1.dist-info/METADATA
haja_workers-0.1.1.dist-info/WHEEL
haja_workers-0.1.1.dist-info/top_level.txt
haja_workers-0.1.1.dist-info/RECORD
