Metadata-Version: 2.4
Name: haja_workers
Version: 0.1.1
Summary: Haja Workers SDK - Python implementation for workflow functions
Author: Fatshark Studios AB
Project-URL: Homepage, https://github.com/FatsharkStudiosAB/haja-workers
Project-URL: Repository, https://github.com/FatsharkStudiosAB/haja-workers
Requires-Python: >=3.10
Requires-Dist: grpcio>=1.60
Requires-Dist: grpcio-tools>=1.60
Requires-Dist: pydantic>=2
Requires-Dist: python-dotenv>=1.0.0
